kasalkar_utils_lib/sdk/kasalkar_utils.py
kasalkar_utils_lib-2.0.0.dist-info/METADATA
kasalkar_utils_lib-2.0.0.dist-info/WHEEL
kasalkar_utils_lib-2.0.0.dist-info/top_level.txt
kasalkar_utils_lib-2.0.0.dist-info/RECORD
